odoo9_addon_sale_analytic_distribution-9.0.1.0.0-py2.7-nspkg.pth
odoo9_addon_sale_analytic_distribution-9.0.1.0.0.dist-info/DESCRIPTION.rst
odoo9_addon_sale_analytic_distribution-9.0.1.0.0.dist-info/METADATA
odoo9_addon_sale_analytic_distribution-9.0.1.0.0.dist-info/RECORD
odoo9_addon_sale_analytic_distribution-9.0.1.0.0.dist-info/WHEEL
odoo9_addon_sale_analytic_distribution-9.0.1.0.0.dist-info/metadata.json
odoo9_addon_sale_analytic_distribution-9.0.1.0.0.dist-info/namespace_packages.txt
odoo9_addon_sale_analytic_distribution-9.0.1.0.0.dist-info/top_level.txt
odoo_addons/sale_analytic_distribution/README.rst
odoo_addons/sale_analytic_distribution/__init__.py
odoo_addons/sale_analytic_distribution/__openerp__.py
odoo_addons/sale_analytic_distribution/i18n/af.po
odoo_addons/sale_analytic_distribution/i18n/ar.po
odoo_addons/sale_analytic_distribution/i18n/bg.po
odoo_addons/sale_analytic_distribution/i18n/bs.po
odoo_addons/sale_analytic_distribution/i18n/ca.po
odoo_addons/sale_analytic_distribution/i18n/cs.po
odoo_addons/sale_analytic_distribution/i18n/da.po
odoo_addons/sale_analytic_distribution/i18n/de.po
odoo_addons/sale_analytic_distribution/i18n/el.po
odoo_addons/sale_analytic_distribution/i18n/en_GB.po
odoo_addons/sale_analytic_distribution/i18n/es.po
odoo_addons/sale_analytic_distribution/i18n/es_AR.po
odoo_addons/sale_analytic_distribution/i18n/es_BO.po
odoo_addons/sale_analytic_distribution/i18n/es_CL.po
odoo_addons/sale_analytic_distribution/i18n/es_CO.po
odoo_addons/sale_analytic_distribution/i18n/es_CR.po
odoo_addons/sale_analytic_distribution/i18n/es_DO.po
odoo_addons/sale_analytic_distribution/i18n/es_EC.po
odoo_addons/sale_analytic_distribution/i18n/es_MX.po
odoo_addons/sale_analytic_distribution/i18n/es_PE.po
odoo_addons/sale_analytic_distribution/i18n/es_PY.po
odoo_addons/sale_analytic_distribution/i18n/es_VE.po
odoo_addons/sale_analytic_distribution/i18n/et.po
odoo_addons/sale_analytic_distribution/i18n/eu.po
odoo_addons/sale_analytic_distribution/i18n/fa.po
odoo_addons/sale_analytic_distribution/i18n/fi.po
odoo_addons/sale_analytic_distribution/i18n/fr.po
odoo_addons/sale_analytic_distribution/i18n/fr_BE.po
odoo_addons/sale_analytic_distribution/i18n/fr_CA.po
odoo_addons/sale_analytic_distribution/i18n/gl.po
odoo_addons/sale_analytic_distribution/i18n/gu.po
odoo_addons/sale_analytic_distribution/i18n/he.po
odoo_addons/sale_analytic_distribution/i18n/hi.po
odoo_addons/sale_analytic_distribution/i18n/hr.po
